paniko/__init__.py
paniko/paniko.py
paniko-1.0.1.dist-info/LICENSE
paniko-1.0.1.dist-info/METADATA
paniko-1.0.1.dist-info/WHEEL
paniko-1.0.1.dist-info/top_level.txt
paniko-1.0.1.dist-info/RECORD
