Metadata-Version: 2.1
Name: paniko
Version: 1.0.1
Summary: Python Kaniko https://github.com/GoogleContainerTools/Kaniko
Author: William Clark
Author-email: wfclark5@outlook.com
Maintainer: William Clark
Maintainer-email: wfclark5@outlook.com
License: Apache 2.0
License-File: LICENSE
